mlsgraphcreator/__init__.py
mlsgraphcreator/__main__.py
mlsgraphcreator/graphcreator.py
mlsgraphcreator-1.0.5.dist-info/METADATA
mlsgraphcreator-1.0.5.dist-info/WHEEL
mlsgraphcreator-1.0.5.dist-info/entry_points.txt
mlsgraphcreator-1.0.5.dist-info/top_level.txt
mlsgraphcreator-1.0.5.dist-info/RECORD
